split_words/__init__.py
split_words/ngram_probs.json
split_words/splitter.py
split_words/training.py
split_words-0.1.3.dist-info/LICENSE
split_words-0.1.3.dist-info/METADATA
split_words-0.1.3.dist-info/WHEEL
split_words-0.1.3.dist-info/RECORD
