Metadata-Version: 2.1
Name: split-words
Version: 0.1.3
Summary: Split German words
Home-page: https://github.com/ffreemt/split-words
Author: Refer to CharSplit repo
Requires-Python: >=3.8.3,<4.0.0
Classifier: Programming Language :: Python :: 3
Classifier: Programming Language :: Python :: 3.9
Classifier: Programming Language :: Python :: 3.10
Classifier: Programming Language :: Python :: 3.11
Project-URL: Repository, https://github.com/ffreemt/split-words
